QForestML/__init__.py
QForestML/qnn.py
QForestML-0.0.1.dist-info/LICENSE
QForestML-0.0.1.dist-info/METADATA
QForestML-0.0.1.dist-info/WHEEL
QForestML-0.0.1.dist-info/top_level.txt
QForestML-0.0.1.dist-info/RECORD
