Metadata-Version: 2.1
Name: QForestML
Version: 0.0.1
Summary: A wrapper for machine learning models in Qiskit.
Home-page: https://github.com/QForestCommunity/QForestML
Author: Sashwat Anagolum
Author-email: sashwat.anagolum@gmail.com
License: UNKNOWN
Platform: UNKNOWN
Classifier: Programming Language :: Python :: 3
Classifier: License :: OSI Approved :: MIT License
Classifier: Operating System :: OS Independent
Requires-Python: >=3.6
